MuxesLogic/probador.v
module ClkGen_Probador(			        input clk4f,
						input clk2f, 
						input clkf,
						input clk4fe,
						input clk2fe,
						input clkfe,
						input [8:0] outEtapaL2,
						input [8:0] outEtapaL2Estru,
						output reg reset_L, 
						output reg clk16f,
						output reg [8:0] data0,
						output reg [8:0] data1,
						output reg [8:0] data2,
						output reg [8:0] data3
						);

initial clk16f <=1;
always begin
	#2 clk16f <= ~clk16f;
end

initial begin
	$dumpfile("ClkGen.vcd");
	$dumpvars;

	reset_L = 1'b0;
	data0 <= 9'b100000000;
	data1 <= 9'b100000001;
	data2 <= 9'b100000010;
	data3 <= 9'b100000011;

	#4 reset_L = 1'b1;


	@(posedge clkf) begin
	data0 <= 9'b111000000;
	data1 <= 9'b100000010;
	data2 <= 9'b100000001;
	data3 <= 9'b100000000;
	end

	@(posedge clkf) begin
	data0 <= 9'b111000000;
	data1 <= 9'b100000001;
	data2 <= 9'b100000010;
	data3 <= 9'b100000011;
	end

	@(posedge clkf) begin
	data0 <= 9'b111000000;
	data1 <= 9'b100000010;
	data2 <= 9'b100000001;
	data3 <= 9'b100000000;
	end

	#10000 $finish;
end

endmodule

MuxesLogic/phy_tx.v



module phy_tx(	input clk_f,
		input clk_2f,
		input clk_4f,
		input reset,	
		input [8:0] data0,
		input [8:0] data1,
		input [8:0] data2,
		input [8:0] data3,
		output reg [8:0] outEtapaL2);


	reg [8:0] outEtapaL1L2_0, outEtapaL1L2_1;
	reg selectorL1, selectorL2;
	reg [8:0] etapa1_preData0, etapa1_preData1, etapa1_preData2, etapa1_preData3;
	reg [8:0] etapa2_preData0, etapa2_preData1;

	always @(posedge clk_f) begin
		etapa1_preData0 <= (data0[8] ? data0 : {1'b0, etapa1_preData0[7:0]});
		etapa1_preData1 <= (data1[8] ? data1 : {1'b0, etapa1_preData1[7:0]});
		etapa1_preData2 <= (data2[8] ? data2 : {1'b0, etapa1_preData2[7:0]});
		etapa1_preData3 <= (data3[8] ? data3 : {1'b0, etapa1_preData3[7:0]});


		if (~reset) begin
			etapa1_preData0 <= 0;
			etapa1_preData1 <= 0;
			etapa1_preData2 <= 0;
			etapa1_preData3 <= 0;
			selectorL1 <= 0;

		end
		else
			selectorL1 <= ~selectorL1;	
	

	end
	
	always @(posedge clk_2f) begin
		etapa2_preData0 <= (outEtapaL1L2_0[8] ? outEtapaL1L2_0 : {1'b0, etapa2_preData0[7:0]});
		etapa2_preData1 <= (outEtapaL1L2_1[8] ? outEtapaL1L2_1 : {1'b0, etapa2_preData1[7:0]});

		if (~reset) begin
			etapa2_preData0 <= 0;
			etapa2_preData1 <= 0;
			selectorL2 <= 0;
		end
		else
			selectorL2 <= ~selectorL2;	

	end

/////////////////////////////////////////////////////////////////////

	always @(*) begin
		if (~reset) begin
			outEtapaL1L2_0 = 0;
			outEtapaL1L2_1 = 0;
			outEtapaL2 = 0;
		end
		else begin
			if(selectorL1) begin
				outEtapaL1L2_0 = (data1[1] ? data1 : etapa1_preData1);
				outEtapaL1L2_1 = (data3[1] ? data3 : etapa1_preData3);
			end
			else begin
				outEtapaL1L2_0 = (data0[1] ? data0 : etapa1_preData0);
				outEtapaL1L2_1 = (data2[1] ? data2 : etapa1_preData2);

			end
			
			if(selectorL2)
				outEtapaL2 = (outEtapaL1L2_1[8] ? outEtapaL1L2_1: etapa2_preData1);
			else
				outEtapaL2 = (outEtapaL1L2_0[8] ? outEtapaL1L2_0: etapa2_preData0);
		end	
	
	end


endmodule

ClockGenerator/ClkGenerator.v
module ClkGenerator(	input 		clk16f,
						input 		reset_L,
						output reg 	clk4f,
						output reg 	clk2f,
						output reg 	clkf
						);

	//Contadores
	reg counter1;
	reg [1:0] counter2;
	reg [2:0] counter3;

	//Reset contadores y relojes 4f, 2f y f
	always @ (posedge clk16f) begin
		if(!reset_L)begin
		counter1<=0;
		counter2<=0;
		counter3<=0;
		clk4f<=1;
		clk2f<=1;
		clkf<=1;
		end
	end

	//Generacion reloj clk4f
	always @ (posedge clk16f) begin
		if(counter1>=1)begin
			clk4f <= ~clk4f;
			counter1<=0;
		end 
		else begin
			counter1<=counter1+1;
		end 
	end

	//Generacion reloj clk2f
	always @ (posedge clk16f) begin
		if(counter2>=3)begin
			clk2f <= ~clk2f;
			counter2<=0;
		end 
		else begin
			counter2<=counter2+1;
		end 
	end

	//Generacion reloj clkf
	always @ (posedge clk16f) begin
		if(counter3>=7)begin
			clkf <= ~clkf;
			counter3<=0;
		end 
		else begin
			counter3<=counter3+1;
		end 
	end

endmodule

MuxesLogic/testbench.v
`timescale 1ns / 100ps
`include "ClkGenerator.v"
`include "phy_tx.v"
`include "probador.v"

module Test_Bench;
	
	wire reset_L, clkf, clk4f, clk2f;
	wire [8:0] data0, data1, data2, data3, outEtapaL2;
	

	//Instancia modulo ClkGenerator
	ClkGenerator	 CG 	( 	.clk16f	(clk16f),
				        .reset_L(reset_L),
				        .clk4f(clk4f),
					.clk2f(clk2f),
					.clkf(clkf)
	);


phy_tx tx(.clk_f(clkf),
          .clk_2f(clk2f),
	  .clk_4f(clk4f),
	  .reset(reset_L),
	  .data0(data0),
	  .data1(data1),
	  .data2(data2),
	  .data3(data3),
	  .outEtapaL2(outEtapaL2));


	//Instancia probador
	ClkGen_Probador	 CG_Probador( 	.clk16f	(clk16f),
									.clk4f	(clk4f),
									.clk2f	(clk2f),
									.clkf 	(clkf),
									.reset_L(reset_L),
									.clk4fe	(clk4fest),
									.clk2fe	(clk2fest),
									.clkfe (clkfest),
									.data0(data0),
	  								.data1(data1),
	  								.data2(data2),
	  								.data3(data3),
									.outEtapaL2(outEtapaL2)

	);

endmodule

MuxesLogic/ClkGen.vcd
$date
	Wed Oct 10 11:36:43 2018
$end
$version
	Icarus Verilog
$end
$timescale
	100ps
$end
$scope module Test_Bench $end
$var wire 1 ! clk2fest $end
$var wire 1 " clk4fest $end
$var wire 1 # clkfest $end
$var wire 1 $ reset_L $end
$var wire 9 % outEtapaL2 [8:0] $end
$var wire 9 & data3 [8:0] $end
$var wire 9 ' data2 [8:0] $end
$var wire 9 ( data1 [8:0] $end
$var wire 9 ) data0 [8:0] $end
$var wire 1 * clkf $end
$var wire 1 + clk4f $end
$var wire 1 , clk2f $end
$var wire 1 - clk16f $end
$scope module CG $end
$var wire 1 $ reset_L $end
$var wire 1 - clk16f $end
$var reg 1 , clk2f $end
$var reg 1 + clk4f $end
$var reg 1 * clkf $end
$var reg 1 . counter1 $end
$var reg 2 / counter2 [1:0] $end
$var reg 3 0 counter3 [2:0] $end
$upscope $end
$scope module CG_Probador $end
$var wire 1 , clk2f $end
$var wire 1 ! clk2fe $end
$var wire 1 + clk4f $end
$var wire 1 " clk4fe $end
$var wire 1 * clkf $end
$var wire 1 # clkfe $end
$var wire 9 1 outEtapaL2 [8:0] $end
$var reg 1 - clk16f $end
$var reg 9 2 data0 [8:0] $end
$var reg 9 3 data1 [8:0] $end
$var reg 9 4 data2 [8:0] $end
$var reg 9 5 data3 [8:0] $end
$var reg 1 $ reset_L $end
$upscope $end
$scope module tx $end
$var wire 1 , clk_2f $end
$var wire 1 + clk_4f $end
$var wire 1 * clk_f $end
$var wire 9 6 data0 [8:0] $end
$var wire 9 7 data1 [8:0] $end
$var wire 9 8 data2 [8:0] $end
$var wire 9 9 data3 [8:0] $end
$var wire 1 $ reset $end
$var reg 9 : etapa1_preData0 [8:0] $end
$var reg 9 ; etapa1_preData1 [8:0] $end
$var reg 9 < etapa1_preData2 [8:0] $end
$var reg 9 = etapa1_preData3 [8:0] $end
$var reg 9 > etapa2_preData0 [8:0] $end
$var reg 9 ? etapa2_preData1 [8:0] $end
$var reg 9 @ outEtapaL1L2_0 [8:0] $end
$var reg 9 A outEtapaL1L2_1 [8:0] $end
$var reg 9 B outEtapaL2 [8:0] $end
$var reg 1 C selectorL1 $end
$var reg 1 D selectorL2 $end
$upscope $end
$upscope $end
$enddefinitions $end
#0
$dumpvars
xD
xC
b0 B
b0 A
b0 @
bx ?
bx >
bx =
bx <
bx ;
bx :
b100000011 9
b100000010 8
b100000001 7
b100000000 6
b100000011 5
b100000010 4
b100000001 3
b100000000 2
b0 1
bx 0
bx /
x.
0-
x,
x+
x*
b100000000 )
b100000001 (
b100000010 '
b100000011 &
b0 %
0$
z#
z"
z!
$end
#20
0C
b0 =
b0 <
b0 ;
b0 :
0D
b0 ?
b0 >
1*
1,
1+
b0 0
b0 /
0.
1-
#40
0-
b100000010 A
1$
#60
b1 0
b1 /
1.
1-
#80
0-
#100
b10 0
b10 /
0.
0+
1-
#120
0-
#140
b11 0
b11 /
1.
1-
#160
0-
#180
b100 0
b0 /
0,
0.
1+
1-
#200
0-
#220
b101 0
b1 /
1.
1-
#240
0-
#260
b110 0
b10 /
0.
0+
1-
#280
0-
#300
b111 0
b11 /
1.
1-
#320
0-
#340
1D
b0 0
0*
b0 /
1,
0.
1+
b10 A
1-
b11 &
b11 5
b11 9
b10 '
b10 4
b10 8
#360
0-
#380
b1 0
b1 /
1.
1-
#400
0-
#420
b10 0
b10 /
0.
0+
1-
#440
0-
#460
b11 0
b11 /
1.
1-
#480
0-
#500
b100 0
b0 /
0,
0.
1+
1-
#520
0-
#540
b101 0
b1 /
1.
1-
#560
0-
#580
b110 0
b10 /
0.
0+
1-
#600
0-
#620
b111 0
b11 /
1.
1-
#640
b100000010 %
b100000010 1
b100000010 B
b100000010 A
0-
b100000011 &
b100000011 5
b100000011 9
b100000010 '
b100000010 4
b100000010 8
b1 (
b1 3
b1 7
b0 )
b0 2
b0 6
#660
b0 %
b0 1
b0 B
b100000011 A
1C
b100000011 =
b100000010 <
0D
b100000010 ?
b0 0
1*
b0 /
1,
0.
1+
1-
#680
0-
#700
b1 0
b1 /
1.
1-
#720
0-
#740
b10 0
b10 /
0.
0+
1-
#760
0-
#780
b11 0
b11 /
1.
1-
#800
0-
#820
b100 0
b0 /
0,
0.
1+
1-
#840
0-
#860
b101 0
b1 /
1.
1-
#880
0-
#900
b110 0
b10 /
0.
0+
1-
#920
0-
#940
b111 0
b11 /
1.
b11 A
1-
b11 &
b11 5
b11 9
b10 '
b10 4
b10 8
b100000000 )
b100000000 2
b100000000 6
#960
0-
#980
b10 %
b10 1
b10 B
1D
b10 ?
b0 0
0*
b0 /
1,
0.
1+
1-
#1000
0-
#1020
b1 0
b1 /
1.
1-
#1040
0-
#1060
b10 0
b10 /
0.
0+
1-
#1080
0-
#1100
b11 0
b11 /
1.
1-
#1120
0-
#1140
b100 0
b0 /
0,
0.
1+
1-
#1160
0-
#1180
b101 0
b1 /
1.
1-
#1200
0-
#1220
b110 0
b10 /
0.
0+
1-
#1240
0-
#1260
b111 0
b11 /
1.
1-
#1280
0-
#1300
b100000000 %
b100000000 1
b100000000 B
b10 A
b100000000 @
0C
b11 =
b10 <
b100000000 :
0D
b0 0
1*
b0 /
1,
0.
1+
1-
#1320
0-
#1340
b1 0
b1 /
1.
1-
#1360
0-
#1380
b10 0
b10 /
0.
0+
1-
#1400
0-
#1420
b11 0
b11 /
1.
1-
#1440
0-
#1460
b100 0
b0 /
0,
0.
1+
1-
#1480
0-
#1500
b101 0
b1 /
1.
1-
#1520
0-
#1540
b110 0
b10 /
0.
0+
1-
#1560
0-
#1580
b111 0
b11 /
1.
1-
#1600
0-
#1620
b10 %
b10 1
b10 B
1D
b100000000 >
b0 0
0*
b0 /
1,
0.
1+
1-
#1640
0-
#1660
b1 0
b1 /
1.
1-
#1680
0-
#1700
b10 0
b10 /
0.
0+
1-
#1720
0-
#1740
b11 0
b11 /
1.
1-
#1760
0-
#1780
b100 0
b0 /
0,
0.
1+
1-
#1800
0-
#1820
b101 0
b1 /
1.
1-
#1840
0-
#1860
b110 0
b10 /
0.
0+
1-
#1880
0-
#1900
b111 0
b11 /
1.
1-
#1920
0-
#1940
b0 %
b0 1
b0 B
b11 A
b0 @
1C
0D
b0 0
1*
b0 /
1,
0.
1+
1-
#1960
0-
#1980
b1 0
b1 /
1.
1-
#2000
0-
#2020
b10 0
b10 /
0.
0+
1-
#2040
0-
#2060
b11 0
b11 /
1.
1-
#2080
0-
#2100
b100 0
b0 /
0,
0.
1+
1-
#2120
0-
#2140
b101 0
b1 /
1.
1-
#2160
0-
#2180
b110 0
b10 /
0.
0+
1-
#2200
0-
#2220
b111 0
b11 /
1.
1-
#2240
0-
#2260
b10 %
b10 1
b10 B
1D
b0 >
b0 0
0*
b0 /
1,
0.
1+
1-
#2280
0-
#2300
b1 0
b1 /
1.
1-
#2320
0-
#2340
b10 0
b10 /
0.
0+
1-
#2360
0-
#2380
b11 0
b11 /
1.
1-
#2400
0-
#2420
b100 0
b0 /
0,
0.
1+
1-
#2440
0-
#2460
b101 0
b1 /
1.
1-
#2480
0-
#2500
b110 0
b10 /
0.
0+
1-
#2520
0-
#2540
b111 0
b11 /
1.
1-
#2560
0-
#2580
b100000000 %
b100000000 1
b100000000 B
b10 A
b100000000 @
0C
0D
b0 0
1*
b0 /
1,
0.
1+
1-
#2600
0-
#2620
b1 0
b1 /
1.
1-
#2640
0-
#2660
b10 0
b10 /
0.
0+
1-
#2680
0-
#2700
b11 0
b11 /
1.
1-
#2720
0-
#2740
b100 0
b0 /
0,
0.
1+
1-
#2760
0-
#2780
b101 0
b1 /
1.
1-
#2800
0-
#2820
b110 0
b10 /
0.
0+
1-
#2840
0-
#2860
b111 0
b11 /
1.
1-
#2880
0-
#2900
b10 %
b10 1
b10 B
1D
b100000000 >
b0 0
0*
b0 /
1,
0.
1+
1-
#2920
0-
#2940
b1 0
b1 /
1.
1-
#2960
0-
#2980
b10 0
b10 /
0.
0+
1-
#3000
0-
#3020
b11 0
b11 /
1.
1-
#3040
0-
#3060
b100 0
b0 /
0,
0.
1+
1-
#3080
0-
#3100
b101 0
b1 /
1.
1-
#3120
0-
#3140
b110 0
b10 /
0.
0+
1-
#3160
0-
#3180
b111 0
b11 /
1.
1-
#3200
0-
#3220
b0 %
b0 1
b0 B
b11 A
b0 @
1C
0D
b0 0
1*
b0 /
1,
0.
1+
1-
#3240
0-
#3260
b1 0
b1 /
1.
1-
#3280
0-
#3300
b10 0
b10 /
0.
0+
1-
#3320
0-
#3340
b11 0
b11 /
1.
1-
#3360
0-
#3380
b100 0
b0 /
0,
0.
1+
1-
#3400
0-
#3420
b101 0
b1 /
1.
1-
#3440
0-
#3460
b110 0
b10 /
0.
0+
1-
#3480
0-
#3500
b111 0
b11 /
1.
1-
#3520
0-
#3540
b10 %
b10 1
b10 B
1D
b0 >
b0 0
0*
b0 /
1,
0.
1+
1-
#3560
0-
#3580
b1 0
b1 /
1.
1-
#3600
0-
#3620
b10 0
b10 /
0.
0+
1-
#3640
0-
#3660
b11 0
b11 /
1.
1-
#3680
0-
#3700
b100 0
b0 /
0,
0.
1+
1-
#3720
0-
#3740
b101 0
b1 /
1.
1-
#3760
0-
#3780
b110 0
b10 /
0.
0+
1-
#3800
0-
#3820
b111 0
b11 /
1.
1-
#3840
0-
#3860
b100000000 %
b100000000 1
b100000000 B
b10 A
b100000000 @
0C
0D
b0 0
1*
b0 /
1,
0.
1+
1-
#3880
0-
#3900
b1 0
b1 /
1.
1-
#3920
0-
#3940
b10 0
b10 /
0.
0+
1-
#3960
0-
#3980
b11 0
b11 /
1.
1-
#4000
0-
#4020
b100 0
b0 /
0,
0.
1+
1-
#4040
0-
#4060
b101 0
b1 /
1.
1-
#4080
0-
#4100
b110 0
b10 /
0.
0+
1-
#4120
0-
#4140
b111 0
b11 /
1.
1-
#4160
0-
#4180
b10 %
b10 1
b10 B
1D
b100000000 >
b0 0
0*
b0 /
1,
0.
1+
1-
#4200
0-
#4220
b1 0
b1 /
1.
1-
#4240
0-
#4260
b10 0
b10 /
0.
0+
1-
#4280
0-
#4300
b11 0
b11 /
1.
1-
#4320
0-
#4340
b100 0
b0 /
0,
0.
1+
1-
#4360
0-
#4380
b101 0
b1 /
1.
1-
#4400
0-
#4420
b110 0
b10 /
0.
0+
1-
#4440
0-
#4460
b111 0
b11 /
1.
1-
#4480
0-
#4500
b0 %
b0 1
b0 B
b11 A
b0 @
1C
0D
b0 0
1*
b0 /
1,
0.
1+
1-
#4520
0-
#4540
b1 0
b1 /
1.
1-
#4560
0-
#4580
b10 0
b10 /
0.
0+
1-
#4600
0-
#4620
b11 0
b11 /
1.
1-
#4640
0-
#4660
b100 0
b0 /
0,
0.
1+
1-
#4680
0-
#4700
b101 0
b1 /
1.
1-
#4720
0-
#4740
b110 0
b10 /
0.
0+
1-
#4760
0-
#4780
b111 0
b11 /
1.
1-
#4800
0-
#4820
b10 %
b10 1
b10 B
1D
b0 >
b0 0
0*
b0 /
1,
0.
1+
1-
#4840
0-
#4860
b1 0
b1 /
1.
1-
#4880
0-
#4900
b10 0
b10 /
0.
0+
1-
#4920
0-
#4940
b11 0
b11 /
1.
1-
#4960
0-
#4980
b100 0
b0 /
0,
0.
1+
1-
#5000
0-
#5020
b101 0
b1 /
1.
1-
#5040
0-
#5060
b110 0
b10 /
0.
0+
1-
#5080
0-
#5100
b111 0
b11 /
1.
1-
#5120
0-
#5140
b100000000 %
b100000000 1
b100000000 B
b10 A
b100000000 @
0C
0D
b0 0
1*
b0 /
1,
0.
1+
1-
#5160
0-
#5180
b1 0
b1 /
1.
1-
#5200
0-
#5220
b10 0
b10 /
0.
0+
1-
#5240
0-
#5260
b11 0
b11 /
1.
1-
#5280
0-
#5300
b100 0
b0 /
0,
0.
1+
1-
#5320
0-
#5340
b101 0
b1 /
1.
1-
#5360
0-
#5380
b110 0
b10 /
0.
0+
1-
#5400
0-
#5420
b111 0
b11 /
1.
1-
#5440
0-
#5460
b10 %
b10 1
b10 B
1D
b100000000 >
b0 0
0*
b0 /
1,
0.
1+
1-
#5480
0-
#5500
b1 0
b1 /
1.
1-
#5520
0-
#5540
b10 0
b10 /
0.
0+
1-
#5560
0-
#5580
b11 0
b11 /
1.
1-
#5600
0-
#5620
b100 0
b0 /
0,
0.
1+
1-
#5640
0-
#5660
b101 0
b1 /
1.
1-
#5680
0-
#5700
b110 0
b10 /
0.
0+
1-
#5720
0-
#5740
b111 0
b11 /
1.
1-
#5760
0-
#5780
b0 %
b0 1
b0 B
b11 A
b0 @
1C
0D
b0 0
1*
b0 /
1,
0.
1+
1-
#5800
0-
#5820
b1 0
b1 /
1.
1-
#5840
0-
#5860
b10 0
b10 /
0.
0+
1-
#5880
0-
#5900
b11 0
b11 /
1.
1-
#5920
0-
#5940
b100 0
b0 /
0,
0.
1+
1-
#5960
0-
#5980
b101 0
b1 /
1.
1-
#6000
0-
#6020
b110 0
b10 /
0.
0+
1-
#6040
0-
#6060
b111 0
b11 /
1.
1-
#6080
0-
#6100
b10 %
b10 1
b10 B
1D
b0 >
b0 0
0*
b0 /
1,
0.
1+
1-
#6120
0-
#6140
b1 0
b1 /
1.
1-
#6160
0-
#6180
b10 0
b10 /
0.
0+
1-
#6200
0-
#6220
b11 0
b11 /
1.
1-
#6240
0-
#6260
b100 0
b0 /
0,
0.
1+
1-
#6280
0-
#6300
b101 0
b1 /
1.
1-
#6320
0-
#6340
b110 0
b10 /
0.
0+
1-
#6360
0-
#6380
b111 0
b11 /
1.
1-
#6400
0-
#6420
b100000000 %
b100000000 1
b100000000 B
b10 A
b100000000 @
0C
0D
b0 0
1*
b0 /
1,
0.
1+
1-
#6440
0-
#6460
b1 0
b1 /
1.
1-
#6480
0-
#6500
b10 0
b10 /
0.
0+
1-
#6520
0-
#6540
b11 0
b11 /
1.
1-
#6560
0-
#6580
b100 0
b0 /
0,
0.
1+
1-
#6600
0-
#6620
b101 0
b1 /
1.
1-
#6640
0-
#6660
b110 0
b10 /
0.
0+
1-
#6680
0-
#6700
b111 0
b11 /
1.
1-
#6720
0-
#6740
b10 %
b10 1
b10 B
1D
b100000000 >
b0 0
0*
b0 /
1,
0.
1+
1-
#6760
0-
#6780
b1 0
b1 /
1.
1-
#6800
0-
#6820
b10 0
b10 /
0.
0+
1-
#6840
0-
#6860
b11 0
b11 /
1.
1-
#6880
0-
#6900
b100 0
b0 /
0,
0.
1+
1-
#6920
0-
#6940
b101 0
b1 /
1.
1-
#6960
0-
#6980
b110 0
b10 /
0.
0+
1-
#7000
0-
#7020
b111 0
b11 /
1.
1-
#7040
0-
#7060
b0 %
b0 1
b0 B
b11 A
b0 @
1C
0D
b0 0
1*
b0 /
1,
0.
1+
1-
#7080
0-
#7100
b1 0
b1 /
1.
1-
#7120
0-
#7140
b10 0
b10 /
0.
0+
1-
#7160
0-
#7180
b11 0
b11 /
1.
1-
#7200
0-
#7220
b100 0
b0 /
0,
0.
1+
1-
#7240
0-
#7260
b101 0
b1 /
1.
1-
#7280
0-
#7300
b110 0
b10 /
0.
0+
1-
#7320
0-
#7340
b111 0
b11 /
1.
1-
#7360
0-
#7380
b10 %
b10 1
b10 B
1D
b0 >
b0 0
0*
b0 /
1,
0.
1+
1-
#7400
0-
#7420
b1 0
b1 /
1.
1-
#7440
0-
#7460
b10 0
b10 /
0.
0+
1-
#7480
0-
#7500
b11 0
b11 /
1.
1-
#7520
0-
#7540
b100 0
b0 /
0,
0.
1+
1-
#7560
0-
#7580
b101 0
b1 /
1.
1-
#7600
0-
#7620
b110 0
b10 /
0.
0+
1-
#7640
0-
#7660
b111 0
b11 /
1.
1-
#7680
0-
#7700
b100000000 %
b100000000 1
b100000000 B
b10 A
b100000000 @
0C
0D
b0 0
1*
b0 /
1,
0.
1+
1-
#7720
0-
#7740
b1 0
b1 /
1.
1-
#7760
0-
#7780
b10 0
b10 /
0.
0+
1-
#7800
0-
#7820
b11 0
b11 /
1.
1-
#7840
0-
#7860
b100 0
b0 /
0,
0.
1+
1-
#7880
0-
#7900
b101 0
b1 /
1.
1-
#7920
0-
#7940
b110 0
b10 /
0.
0+
1-
#7960
0-
#7980
b111 0
b11 /
1.
1-
#8000
0-
#8020
b10 %
b10 1
b10 B
1D
b100000000 >
b0 0
0*
b0 /
1,
0.
1+
1-
#8040
0-
#8060
b1 0
b1 /
1.
1-
#8080
0-
#8100
b10 0
b10 /
0.
0+
1-
#8120
0-
#8140
b11 0
b11 /
1.
1-
#8160
0-
#8180
b100 0
b0 /
0,
0.
1+
1-
#8200
0-
#8220
b101 0
b1 /
1.
1-
#8240
0-
#8260
b110 0
b10 /
0.
0+
1-
#8280
0-
#8300
b111 0
b11 /
1.
1-
#8320
0-
#8340
b0 %
b0 1
b0 B
b11 A
b0 @
1C
0D
b0 0
1*
b0 /
1,
0.
1+
1-
#8360
0-
#8380
b1 0
b1 /
1.
1-
#8400
0-
#8420
b10 0
b10 /
0.
0+
1-
#8440
0-
#8460
b11 0
b11 /
1.
1-
#8480
0-
#8500
b100 0
b0 /
0,
0.
1+
1-
#8520
0-
#8540
b101 0
b1 /
1.
1-
#8560
0-
#8580
b110 0
b10 /
0.
0+
1-
#8600
0-
#8620
b111 0
b11 /
1.
1-
#8640
0-
#8660
b10 %
b10 1
b10 B
1D
b0 >
b0 0
0*
b0 /
1,
0.
1+
1-
#8680
0-
#8700
b1 0
b1 /
1.
1-
#8720
0-
#8740
b10 0
b10 /
0.
0+
1-
#8760
0-
#8780
b11 0
b11 /
1.
1-
#8800
0-
#8820
b100 0
b0 /
0,
0.
1+
1-
#8840
0-
#8860
b101 0
b1 /
1.
1-
#8880
0-
#8900
b110 0
b10 /
0.
0+
1-
#8920
0-
#8940
b111 0
b11 /
1.
1-
#8960
0-
#8980
b100000000 %
b100000000 1
b100000000 B
b10 A
b100000000 @
0C
0D
b0 0
1*
b0 /
1,
0.
1+
1-
#9000
0-
#9020
b1 0
b1 /
1.
1-
#9040
0-
#9060
b10 0
b10 /
0.
0+
1-
#9080
0-
#9100
b11 0
b11 /
1.
1-
#9120
0-
#9140
b100 0
b0 /
0,
0.
1+
1-
#9160
0-
#9180
b101 0
b1 /
1.
1-
#9200
0-
#9220
b110 0
b10 /
0.
0+
1-
#9240
0-
#9260
b111 0
b11 /
1.
1-
#9280
0-
#9300
b10 %
b10 1
b10 B
1D
b100000000 >
b0 0
0*
b0 /
1,
0.
1+
1-
#9320
0-
#9340
b1 0
b1 /
1.
1-
#9360
0-
#9380
b10 0
b10 /
0.
0+
1-
#9400
0-
#9420
b11 0
b11 /
1.
1-
#9440
0-
#9460
b100 0
b0 /
0,
0.
1+
1-
#9480
0-
#9500
b101 0
b1 /
1.
1-
#9520
0-
#9540
b110 0
b10 /
0.
0+
1-
#9560
0-
#9580
b111 0
b11 /
1.
1-
#9600
0-
#9620
b0 %
b0 1
b0 B
b11 A
b0 @
1C
0D
b0 0
1*
b0 /
1,
0.
1+
1-
#9640
0-
#9660
b1 0
b1 /
1.
1-
#9680
0-
#9700
b10 0
b10 /
0.
0+
1-
#9720
0-
#9740
b11 0
b11 /
1.
1-
#9760
0-
#9780
b100 0
b0 /
0,
0.
1+
1-
#9800
0-
#9820
b101 0
b1 /
1.
1-
#9840
0-
#9860
b110 0
b10 /
0.
0+
1-
#9880
0-
#9900
b111 0
b11 /
1.
1-
#9920
0-
#9940
b10 %
b10 1
b10 B
1D
b0 >
b0 0
0*
b0 /
1,
0.
1+
1-
#9960
0-
#9980
b1 0
b1 /
1.
1-
#10000
0-
#10020
b10 0
b10 /
0.
0+
1-
#10040
0-
#10060
b11 0
b11 /
1.
1-
#10080
0-
#10100
b100 0
b0 /
0,
0.
1+
1-
#10120
0-
#10140
b101 0
b1 /
1.
1-
#10160
0-
#10180
b110 0
b10 /
0.
0+
1-
#10200
0-
#10220
b111 0
b11 /
1.
1-
#10240
0-
#10260
b100000000 %
b100000000 1
b100000000 B
b10 A
b100000000 @
0C
0D
b0 0
1*
b0 /
1,
0.
1+
1-
#10280
0-
#10300
b1 0
b1 /
1.
1-
#10320
0-
#10340
b10 0
b10 /
0.
0+
1-
#10360
0-
#10380
b11 0
b11 /
1.
1-
#10400
0-
#10420
b100 0
b0 /
0,
0.
1+
1-
#10440
0-
#10460
b101 0
b1 /
1.
1-
#10480
0-
#10500
b110 0
b10 /
0.
0+
1-
#10520
0-
#10540
b111 0
b11 /
1.
1-
#10560
0-
#10580
b10 %
b10 1
b10 B
1D
b100000000 >
b0 0
0*
b0 /
1,
0.
1+
1-
#10600
0-
#10620
b1 0
b1 /
1.
1-
#10640
0-
#10660
b10 0
b10 /
0.
0+
1-
#10680
0-
#10700
b11 0
b11 /
1.
1-
#10720
0-
#10740
b100 0
b0 /
0,
0.
1+
1-
#10760
0-
#10780
b101 0
b1 /
1.
1-
#10800
0-
#10820
b110 0
b10 /
0.
0+
1-
#10840
0-
#10860
b111 0
b11 /
1.
1-
#10880
0-
#10900
b0 %
b0 1
b0 B
b11 A
b0 @
1C
0D
b0 0
1*
b0 /
1,
0.
1+
1-
#10920
0-
#10940
b1 0
b1 /
1.
1-
#10960
0-
#10980
b10 0
b10 /
0.
0+
1-
#11000
0-
#11020
b11 0
b11 /
1.
1-
#11040
0-
#11060
b100 0
b0 /
0,
0.
1+
1-
#11080
0-
#11100
b101 0
b1 /
1.
1-
#11120
0-
#11140
b110 0
b10 /
0.
0+
1-
#11160
0-
#11180
b111 0
b11 /
1.
1-
#11200
0-
#11220
b10 %
b10 1
b10 B
1D
b0 >
b0 0
0*
b0 /
1,
0.
1+
1-
#11240
0-
#11260
b1 0
b1 /
1.
1-
#11280
0-
#11300
b10 0
b10 /
0.
0+
1-
#11320
0-
#11340
b11 0
b11 /
1.
1-
#11360
0-
#11380
b100 0
b0 /
0,
0.
1+
1-
#11400
0-
#11420
b101 0
b1 /
1.
1-
#11440
0-
#11460
b110 0
b10 /
0.
0+
1-
#11480
0-
#11500
b111 0
b11 /
1.
1-
#11520
0-
#11540
b100000000 %
b100000000 1
b100000000 B
b10 A
b100000000 @
0C
0D
b0 0
1*
b0 /
1,
0.
1+
1-
#11560
0-
#11580
b1 0
b1 /
1.
1-
#11600
0-
#11620
b10 0
b10 /
0.
0+
1-
#11640
0-
#11660
b11 0
b11 /
1.
1-
#11680
0-
#11700
b100 0
b0 /
0,
0.
1+
1-
#11720
0-
#11740
b101 0
b1 /
1.
1-
#11760
0-
#11780
b110 0
b10 /
0.
0+
1-
#11800
0-
#11820
b111 0
b11 /
1.
1-
#11840
0-
#11860
b10 %
b10 1
b10 B
1D
b100000000 >
b0 0
0*
b0 /
1,
0.
1+
1-
#11880
0-
#11900
b1 0
b1 /
1.
1-
#11920
0-
#11940
b10 0
b10 /
0.
0+
1-
#11960
0-
#11980
b11 0
b11 /
1.
1-
#12000
0-
#12020
b100 0
b0 /
0,
0.
1+
1-
#12040
0-
#12060
b101 0
b1 /
1.
1-
#12080
0-
#12100
b110 0
b10 /
0.
0+
1-
#12120
0-
#12140
b111 0
b11 /
1.
1-
#12160
0-
#12180
b0 %
b0 1
b0 B
b11 A
b0 @
1C
0D
b0 0
1*
b0 /
1,
0.
1+
1-
#12200
0-
#12220
b1 0
b1 /
1.
1-
#12240
0-
#12260
b10 0
b10 /
0.
0+
1-
#12280
0-
#12300
b11 0
b11 /
1.
1-
#12320
0-
#12340
b100 0
b0 /
0,
0.
1+
1-
#12360
0-
#12380
b101 0
b1 /
1.
1-
#12400
0-
#12420
b110 0
b10 /
0.
0+
1-
#12440
0-
#12460
b111 0
b11 /
1.
1-
#12480
0-
#12500
b10 %
b10 1
b10 B
1D
b0 >
b0 0
0*
b0 /
1,
0.
1+
1-
#12520
0-
#12540
b1 0
b1 /
1.
1-
#12560
0-
#12580
b10 0
b10 /
0.
0+
1-
#12600
0-
#12620
b11 0
b11 /
1.
1-
#12640
0-
#12660
b100 0
b0 /
0,
0.
1+
1-
#12680
0-
#12700
b101 0
b1 /
1.
1-
#12720
0-
#12740
b110 0
b10 /
0.
0+
1-
#12760
0-
#12780
b111 0
b11 /
1.
1-
