ClockGenerator/ClkGen_Probador.v
module ClkGen_Probador(	input clk4f,
						input clk2f, 
						input clkf,
						input clk4fe,
						input clk2fe,
						input clkfe,
						output reg reset_L, 
						output reg clk16f
						);

initial clk16f <=0;
always begin
	#2 clk16f <= ~clk16f;
end

initial begin
	$dumpfile("ClkGen.vcd");
	$dumpvars;

	reset_L = 1'b0;

	repeat (1) begin
	@(posedge clk16f);
	reset_L <= 1'b1;
	end

	repeat (75) begin
	@(posedge clk16f);

	end

	$finish;
end

endmodule

ClockGenerator/ClkGeneratorEstructural.v
/* Generated by Yosys 0.7+574 (git sha1 0fad1570, gcc 6.3.0-18+deb9u1 -fPIC -Os) */

module ClkGeneratorEstructural(clk16f, reset_L, clk4f, clk2f, clkf);
  wire _00_;
  wire _01_;
  wire _02_;
  wire _03_;
  wire [1:0] _04_;
  wire [2:0] _05_;
  wire [31:0] _06_;
  wire [31:0] _07_;
  wire [31:0] _08_;
  wire [15:0] _09_;
  wire _10_;
  wire _11_;
  wire _12_;
  wire [2:0] _13_;
  wire [1:0] _14_;
  wire _15_;
  wire _16_;
  wire _17_;
  wire _18_;
  input clk16f;
  output clk2f;
  reg clk2f;
  output clk4f;
  reg clk4f;
  output clkf;
  reg clkf;
  reg counter1;
  reg [1:0] counter2;
  reg [2:0] counter3;
  input reset_L;
  assign _09_[0] = counter3[0] & counter3[1];
  assign _13_[0] = _08_[3] ? 1'h0 : _08_[0];
  assign _13_[1] = _08_[3] ? 1'h0 : _08_[1];
  assign _13_[2] = _08_[3] ? 1'h0 : _08_[2];
  assign _05_[0] = reset_L ? _13_[0] : 1'h0;
  assign _05_[1] = reset_L ? _13_[1] : 1'h0;
  assign _05_[2] = reset_L ? _13_[2] : 1'h0;
  assign _14_[0] = _07_[2] ? 1'h0 : _07_[0];
  assign _14_[1] = _07_[2] ? 1'h0 : _07_[1];
  assign _04_[0] = reset_L ? _14_[0] : 1'h0;
  assign _04_[1] = reset_L ? _14_[1] : 1'h0;
  assign _15_ = counter1 ? 1'h0 : _06_[0];
  assign _03_ = reset_L ? _15_ : 1'h0;
  assign _16_ = _08_[3] ? _12_ : clkf;
  assign _02_ = reset_L ? _16_ : 1'h1;
  assign _17_ = _07_[2] ? _11_ : clk2f;
  assign _00_ = reset_L ? _17_ : 1'h1;
  assign _18_ = counter1 ? _10_ : clk4f;
  assign _01_ = reset_L ? _18_ : 1'h1;
  assign _10_ = ~clk4f;
  assign _11_ = ~clk2f;
  assign _12_ = ~clkf;
  always @(posedge clk16f)
      clk4f <= _01_;
  always @(posedge clk16f)
      clk2f <= _00_;
  always @(posedge clk16f)
      clkf <= _02_;
  always @(posedge clk16f)
      counter1 <= _03_;
  always @(posedge clk16f)
      counter2[0] <= _04_[0];
  always @(posedge clk16f)
      counter2[1] <= _04_[1];
  always @(posedge clk16f)
      counter3[0] <= _05_[0];
  always @(posedge clk16f)
      counter3[1] <= _05_[1];
  always @(posedge clk16f)
      counter3[2] <= _05_[2];
  assign _08_[1] = counter3[1] ^ counter3[0];
  assign _08_[0] = counter3[0] ^ 1'h1;
  assign _08_[2] = counter3[2] ^ _09_[0];
  assign _07_[2] = counter2[1] & counter2[0];
  assign _08_[3] = counter3[2] & _09_[0];
  assign _06_[0] = 1'h1 ^ counter1;
  assign _07_[0] = counter2[0] ^ 1'h1;
  assign _07_[1] = counter2[1] ^ counter2[0];
endmodule

ClockGenerator/ClkGenerator.v
module ClkGenerator(	input 		clk16f,
						input 		reset_L,
						output reg 	clk4f,
						output reg 	clk2f,
						output reg 	clkf
						);

	//Contadores
	reg counter1;
	reg [1:0] counter2;
	reg [2:0] counter3;

	//Reset contadores y relojes 4f, 2f y f
	always @ (posedge clk16f) begin
		if(!reset_L)begin
		counter1<=0;
		counter2<=0;
		counter3<=0;
		clk4f<=1;
		clk2f<=1;
		clkf<=1;
		end
	end

	//Generacion reloj clk4f
	always @ (posedge clk16f) begin
		if(counter1>=1)begin
			clk4f <= ~clk4f;
			counter1<=0;
		end 
		else begin
			counter1<=counter1+1;
		end 
	end

	//Generacion reloj clk2f
	always @ (posedge clk16f) begin
		if(counter2>=3)begin
			clk2f <= ~clk2f;
			counter2<=0;
		end 
		else begin
			counter2<=counter2+1;
		end 
	end

	//Generacion reloj clkf
	always @ (posedge clk16f) begin
		if(counter3>=7)begin
			clkf <= ~clkf;
			counter3<=0;
		end 
		else begin
			counter3<=counter3+1;
		end 
	end

endmodule

ClockGenerator/ClkGen_BancoDePruebas.v
`timescale 1ns / 100ps
`include "ClkGenerator.v"
`include "ClkGeneratorEstructural.v"
`include "ClkGen_Probador.v"

module Test_Bench;

	//Instancia modulo ClkGenerator
	ClkGenerator	 CG 	( 	.clk16f	(clk16f),
								.reset_L(reset_L),
								.clk4f	(clk4f),
								.clk2f	(clk2f),
								.clkf 	(clkf)
	);

	//Instancia modulo ClkGenerator Estructural
	ClkGeneratorEstructural	 CGEst 	( 	.clk16f	(clk16f),
										.reset_L(reset_L),
										.clk4f	(clk4fest),
										.clk2f	(clk2fest),
										.clkf 	(clkfest)
	);

	//Instancia probador
	ClkGen_Probador	 CG_Probador( 	.clk16f	(clk16f),
									.clk4f	(clk4f),
									.clk2f	(clk2f),
									.clkf 	(clkf),
									.reset_L(reset_L),
									.clk4fe	(clk4fest),
									.clk2fe	(clk2fest),
									.clkfe (clkfest)

	);

endmodule

ClockGenerator/ClkGen.vcd
$date
	Fri Oct  5 21:15:22 2018
$end
$version
	Icarus Verilog
$end
$timescale
	100ps
$end
$scope module Test_Bench $end
$var wire 1 ! reset_L $end
$var wire 1 " clkfest $end
$var wire 1 # clkf $end
$var wire 1 $ clk4fest $end
$var wire 1 % clk4f $end
$var wire 1 & clk2fest $end
$var wire 1 ' clk2f $end
$var wire 1 ( clk16f $end
$scope module CG $end
$var wire 1 ! reset_L $end
$var wire 1 ( clk16f $end
$var reg 1 ' clk2f $end
$var reg 1 % clk4f $end
$var reg 1 # clkf $end
$var reg 1 ) counter1 $end
$var reg 2 * counter2 [1:0] $end
$var reg 3 + counter3 [2:0] $end
$upscope $end
$scope module CGEst $end
$var wire 1 , _10_ $end
$var wire 1 - _11_ $end
$var wire 1 . _12_ $end
$var wire 1 ! reset_L $end
$var wire 1 ( clk16f $end
$var wire 1 / _18_ $end
$var wire 1 0 _17_ $end
$var wire 1 1 _16_ $end
$var wire 1 2 _15_ $end
$var wire 2 3 _14_ [1:0] $end
$var wire 3 4 _13_ [2:0] $end
$var wire 16 5 _09_ [15:0] $end
$var wire 32 6 _08_ [31:0] $end
$var wire 32 7 _07_ [31:0] $end
$var wire 32 8 _06_ [31:0] $end
$var wire 3 9 _05_ [2:0] $end
$var wire 2 : _04_ [1:0] $end
$var wire 1 ; _03_ $end
$var wire 1 < _02_ $end
$var wire 1 = _01_ $end
$var wire 1 > _00_ $end
$var reg 1 & clk2f $end
$var reg 1 $ clk4f $end
$var reg 1 " clkf $end
$var reg 1 ? counter1 $end
$var reg 2 @ counter2 [1:0] $end
$var reg 3 A counter3 [2:0] $end
$upscope $end
$scope module CG_Probador $end
$var wire 1 ' clk2f $end
$var wire 1 & clk2fe $end
$var wire 1 % clk4f $end
$var wire 1 $ clk4fe $end
$var wire 1 # clkf $end
$var wire 1 " clkfe $end
$var reg 1 ( clk16f $end
$var reg 1 ! reset_L $end
$upscope $end
$upscope $end
$enddefinitions $end
#0
$dumpvars
bx A
bx @
x?
1>
1=
1<
0;
b0 :
b0 9
bzx 8
bzxxx 7
bzxxxx 6
bzx 5
bx 4
bx 3
x2
x1
x0
x/
x.
x-
x,
bx +
bx *
x)
0(
x'
x&
x%
x$
x#
x"
0!
$end
#20
10
b1 3
11
b1 4
12
bz001 7
bz0 5
bz0001 6
0,
0-
0.
1/
bz1 8
1=
1>
1<
1;
b1 :
b1 9
1#
1'
1%
b0 +
b0 *
0)
1$
1&
1"
0?
b0 @
b0 A
1!
1(
#40
0(
#60
b10 9
b10 :
b10 4
b10 3
bz0010 6
bz010 7
0;
0=
02
0/
bz0 8
b1 A
b1 @
1?
b1 +
b1 *
1)
1(
#80
0(
#100
b11 :
b11 9
1;
b11 3
b11 4
12
bz011 7
bz0011 6
1,
bz1 8
b10 +
b10 *
0)
0%
0$
0?
b10 @
b10 A
1(
#120
0(
#140
b100 9
b0 :
0>
b100 4
00
b0 3
bz1 5
bz0100 6
bz100 7
0;
1=
02
1/
bz0 8
b11 A
b11 @
1?
b11 +
b11 *
1)
1(
#160
0(
#180
b1 :
b101 9
1<
1;
b1 3
11
b101 4
0>
12
00
bz001 7
bz0 5
bz0101 6
0,
1-
bz1 8
b100 +
b0 *
0'
0)
1%
1$
0&
0?
b0 @
b100 A
1(
#200
0(
#220
b110 9
b10 :
b110 4
b10 3
bz0110 6
bz010 7
0;
0=
02
0/
bz0 8
b101 A
b1 @
1?
b101 +
b1 *
1)
1(
#240
0(
#260
b11 :
b111 9
1;
b11 3
b111 4
12
bz011 7
bz0111 6
1,
bz1 8
b110 +
b10 *
0)
0%
0$
0?
b10 @
b110 A
1(
#280
0(
#300
0<
01
b0 9
b0 :
1>
b0 4
10
b0 3
bz1 5
bz1000 6
bz100 7
0;
1=
02
1/
bz0 8
b111 A
b11 @
1?
b111 +
b11 *
1)
1(
#320
0(
#340
b1 :
b1 9
1;
b1 3
b1 4
1>
0<
12
10
01
bz001 7
bz0 5
bz0001 6
0,
0-
1.
bz1 8
b0 +
0#
b0 *
1'
0)
1%
1$
1&
0"
0?
b0 @
b0 A
1(
#360
0(
#380
b10 9
b10 :
b10 4
b10 3
bz0010 6
bz010 7
0;
0=
02
0/
bz0 8
b1 A
b1 @
1?
b1 +
b1 *
1)
1(
#400
0(
#420
b11 :
b11 9
1;
b11 3
b11 4
12
bz011 7
bz0011 6
1,
bz1 8
b10 +
b10 *
0)
0%
0$
0?
b10 @
b10 A
1(
#440
0(
#460
b100 9
b0 :
0>
b100 4
00
b0 3
bz1 5
bz0100 6
bz100 7
0;
1=
02
1/
bz0 8
b11 A
b11 @
1?
b11 +
b11 *
1)
1(
#480
0(
#500
b1 :
b101 9
0<
1;
b1 3
01
b101 4
0>
12
00
bz001 7
bz0 5
bz0101 6
0,
1-
bz1 8
b100 +
b0 *
0'
0)
1%
1$
0&
0?
b0 @
b100 A
1(
#520
0(
#540
b110 9
b10 :
b110 4
b10 3
bz0110 6
bz010 7
0;
0=
02
0/
bz0 8
b101 A
b1 @
1?
b101 +
b1 *
1)
1(
#560
0(
#580
b11 :
b111 9
1;
b11 3
b111 4
12
bz011 7
bz0111 6
1,
bz1 8
b110 +
b10 *
0)
0%
0$
0?
b10 @
b110 A
1(
#600
0(
#620
1<
11
b0 9
b0 :
1>
b0 4
10
b0 3
bz1 5
bz1000 6
bz100 7
0;
1=
02
1/
bz0 8
b111 A
b11 @
1?
b111 +
b11 *
1)
1(
#640
0(
#660
b1 :
b1 9
1;
b1 3
b1 4
1>
1<
12
10
11
bz001 7
bz0 5
bz0001 6
0,
0-
0.
bz1 8
b0 +
1#
b0 *
1'
0)
1%
1$
1&
1"
0?
b0 @
b0 A
1(
#680
0(
#700
b10 9
b10 :
b10 4
b10 3
bz0010 6
bz010 7
0;
0=
02
0/
bz0 8
b1 A
b1 @
1?
b1 +
b1 *
1)
1(
#720
0(
#740
b11 :
b11 9
1;
b11 3
b11 4
12
bz011 7
bz0011 6
1,
bz1 8
b10 +
b10 *
0)
0%
0$
0?
b10 @
b10 A
1(
#760
0(
#780
b100 9
b0 :
0>
b100 4
00
b0 3
bz1 5
bz0100 6
bz100 7
0;
1=
02
1/
bz0 8
b11 A
b11 @
1?
b11 +
b11 *
1)
1(
#800
0(
#820
b1 :
b101 9
1<
1;
b1 3
11
b101 4
0>
12
00
bz001 7
bz0 5
bz0101 6
0,
1-
bz1 8
b100 +
b0 *
0'
0)
1%
1$
0&
0?
b0 @
b100 A
1(
#840
0(
#860
b110 9
b10 :
b110 4
b10 3
bz0110 6
bz010 7
0;
0=
02
0/
bz0 8
b101 A
b1 @
1?
b101 +
b1 *
1)
1(
#880
0(
#900
b11 :
b111 9
1;
b11 3
b111 4
12
bz011 7
bz0111 6
1,
bz1 8
b110 +
b10 *
0)
0%
0$
0?
b10 @
b110 A
1(
#920
0(
#940
0<
01
b0 9
b0 :
1>
b0 4
10
b0 3
bz1 5
bz1000 6
bz100 7
0;
1=
02
1/
bz0 8
b111 A
b11 @
1?
b111 +
b11 *
1)
1(
#960
0(
#980
b1 :
b1 9
1;
b1 3
b1 4
1>
0<
12
10
01
bz001 7
bz0 5
bz0001 6
0,
0-
1.
bz1 8
b0 +
0#
b0 *
1'
0)
1%
1$
1&
0"
0?
b0 @
b0 A
1(
#1000
0(
#1020
b10 9
b10 :
b10 4
b10 3
bz0010 6
bz010 7
0;
0=
02
0/
bz0 8
b1 A
b1 @
1?
b1 +
b1 *
1)
1(
#1040
0(
#1060
b11 :
b11 9
1;
b11 3
b11 4
12
bz011 7
bz0011 6
1,
bz1 8
b10 +
b10 *
0)
0%
0$
0?
b10 @
b10 A
1(
#1080
0(
#1100
b100 9
b0 :
0>
b100 4
00
b0 3
bz1 5
bz0100 6
bz100 7
0;
1=
02
1/
bz0 8
b11 A
b11 @
1?
b11 +
b11 *
1)
1(
#1120
0(
#1140
b1 :
b101 9
0<
1;
b1 3
01
b101 4
0>
12
00
bz001 7
bz0 5
bz0101 6
0,
1-
bz1 8
b100 +
b0 *
0'
0)
1%
1$
0&
0?
b0 @
b100 A
1(
#1160
0(
#1180
b110 9
b10 :
b110 4
b10 3
bz0110 6
bz010 7
0;
0=
02
0/
bz0 8
b101 A
b1 @
1?
b101 +
b1 *
1)
1(
#1200
0(
#1220
b11 :
b111 9
1;
b11 3
b111 4
12
bz011 7
bz0111 6
1,
bz1 8
b110 +
b10 *
0)
0%
0$
0?
b10 @
b110 A
1(
#1240
0(
#1260
1<
11
b0 9
b0 :
1>
b0 4
10
b0 3
bz1 5
bz1000 6
bz100 7
0;
1=
02
1/
bz0 8
b111 A
b11 @
1?
b111 +
b11 *
1)
1(
#1280
0(
#1300
b1 :
b1 9
1;
b1 3
b1 4
1>
1<
12
10
11
bz001 7
bz0 5
bz0001 6
0,
0-
0.
bz1 8
b0 +
1#
b0 *
1'
0)
1%
1$
1&
1"
0?
b0 @
b0 A
1(
#1320
0(
#1340
b10 9
b10 :
b10 4
b10 3
bz0010 6
bz010 7
0;
0=
02
0/
bz0 8
b1 A
b1 @
1?
b1 +
b1 *
1)
1(
#1360
0(
#1380
b11 :
b11 9
1;
b11 3
b11 4
12
bz011 7
bz0011 6
1,
bz1 8
b10 +
b10 *
0)
0%
0$
0?
b10 @
b10 A
1(
#1400
0(
#1420
b100 9
b0 :
0>
b100 4
00
b0 3
bz1 5
bz0100 6
bz100 7
0;
1=
02
1/
bz0 8
b11 A
b11 @
1?
b11 +
b11 *
1)
1(
#1440
0(
#1460
b1 :
b101 9
1<
1;
b1 3
11
b101 4
0>
12
00
bz001 7
bz0 5
bz0101 6
0,
1-
bz1 8
b100 +
b0 *
0'
0)
1%
1$
0&
0?
b0 @
b100 A
1(
#1480
0(
#1500
b110 9
b10 :
b110 4
b10 3
bz0110 6
bz010 7
0;
0=
02
0/
bz0 8
b101 A
b1 @
1?
b101 +
b1 *
1)
1(
#1520
0(
#1540
b11 :
b111 9
1;
b11 3
b111 4
12
bz011 7
bz0111 6
1,
bz1 8
b110 +
b10 *
0)
0%
0$
0?
b10 @
b110 A
1(
#1560
0(
#1580
0<
01
b0 9
b0 :
1>
b0 4
10
b0 3
bz1 5
bz1000 6
bz100 7
0;
1=
02
1/
bz0 8
b111 A
b11 @
1?
b111 +
b11 *
1)
1(
#1600
0(
#1620
b1 :
b1 9
1;
b1 3
b1 4
1>
0<
12
10
01
bz001 7
bz0 5
bz0001 6
0,
0-
1.
bz1 8
b0 +
0#
b0 *
1'
0)
1%
1$
1&
0"
0?
b0 @
b0 A
1(
#1640
0(
#1660
b10 9
b10 :
b10 4
b10 3
bz0010 6
bz010 7
0;
0=
02
0/
bz0 8
b1 A
b1 @
1?
b1 +
b1 *
1)
1(
#1680
0(
#1700
b11 :
b11 9
1;
b11 3
b11 4
12
bz011 7
bz0011 6
1,
bz1 8
b10 +
b10 *
0)
0%
0$
0?
b10 @
b10 A
1(
#1720
0(
#1740
b100 9
b0 :
0>
b100 4
00
b0 3
bz1 5
bz0100 6
bz100 7
0;
1=
02
1/
bz0 8
b11 A
b11 @
1?
b11 +
b11 *
1)
1(
#1760
0(
#1780
b1 :
b101 9
0<
1;
b1 3
01
b101 4
0>
12
00
bz001 7
bz0 5
bz0101 6
0,
1-
bz1 8
b100 +
b0 *
0'
0)
1%
1$
0&
0?
b0 @
b100 A
1(
#1800
0(
#1820
b110 9
b10 :
b110 4
b10 3
bz0110 6
bz010 7
0;
0=
02
0/
bz0 8
b101 A
b1 @
1?
b101 +
b1 *
1)
1(
#1840
0(
#1860
b11 :
b111 9
1;
b11 3
b111 4
12
bz011 7
bz0111 6
1,
bz1 8
b110 +
b10 *
0)
0%
0$
0?
b10 @
b110 A
1(
#1880
0(
#1900
1<
11
b0 9
b0 :
1>
b0 4
10
b0 3
bz1 5
bz1000 6
bz100 7
0;
1=
02
1/
bz0 8
b111 A
b11 @
1?
b111 +
b11 *
1)
1(
#1920
0(
#1940
b1 :
b1 9
1;
b1 3
b1 4
1>
1<
12
10
11
bz001 7
bz0 5
bz0001 6
0,
0-
0.
bz1 8
b0 +
1#
b0 *
1'
0)
1%
1$
1&
1"
0?
b0 @
b0 A
1(
#1960
0(
#1980
b10 9
b10 :
b10 4
b10 3
bz0010 6
bz010 7
0;
0=
02
0/
bz0 8
b1 A
b1 @
1?
b1 +
b1 *
1)
1(
#2000
0(
#2020
b11 :
b11 9
1;
b11 3
b11 4
12
bz011 7
bz0011 6
1,
bz1 8
b10 +
b10 *
0)
0%
0$
0?
b10 @
b10 A
1(
#2040
0(
#2060
b100 9
b0 :
0>
b100 4
00
b0 3
bz1 5
bz0100 6
bz100 7
0;
1=
02
1/
bz0 8
b11 A
b11 @
1?
b11 +
b11 *
1)
1(
#2080
0(
#2100
b1 :
b101 9
1<
1;
b1 3
11
b101 4
0>
12
00
bz001 7
bz0 5
bz0101 6
0,
1-
bz1 8
b100 +
b0 *
0'
0)
1%
1$
0&
0?
b0 @
b100 A
1(
#2120
0(
#2140
b110 9
b10 :
b110 4
b10 3
bz0110 6
bz010 7
0;
0=
02
0/
bz0 8
b101 A
b1 @
1?
b101 +
b1 *
1)
1(
#2160
0(
#2180
b11 :
b111 9
1;
b11 3
b111 4
12
bz011 7
bz0111 6
1,
bz1 8
b110 +
b10 *
0)
0%
0$
0?
b10 @
b110 A
1(
#2200
0(
#2220
0<
01
b0 9
b0 :
1>
b0 4
10
b0 3
bz1 5
bz1000 6
bz100 7
0;
1=
02
1/
bz0 8
b111 A
b11 @
1?
b111 +
b11 *
1)
1(
#2240
0(
#2260
b1 :
b1 9
1;
b1 3
b1 4
1>
0<
12
10
01
bz001 7
bz0 5
bz0001 6
0,
0-
1.
bz1 8
b0 +
0#
b0 *
1'
0)
1%
1$
1&
0"
0?
b0 @
b0 A
1(
#2280
0(
#2300
b10 9
b10 :
b10 4
b10 3
bz0010 6
bz010 7
0;
0=
02
0/
bz0 8
b1 A
b1 @
1?
b1 +
b1 *
1)
1(
#2320
0(
#2340
b11 :
b11 9
1;
b11 3
b11 4
12
bz011 7
bz0011 6
1,
bz1 8
b10 +
b10 *
0)
0%
0$
0?
b10 @
b10 A
1(
#2360
0(
#2380
b100 9
b0 :
0>
b100 4
00
b0 3
bz1 5
bz0100 6
bz100 7
0;
1=
02
1/
bz0 8
b11 A
b11 @
1?
b11 +
b11 *
1)
1(
#2400
0(
#2420
b1 :
b101 9
0<
1;
b1 3
01
b101 4
0>
12
00
bz001 7
bz0 5
bz0101 6
0,
1-
bz1 8
b100 +
b0 *
0'
0)
1%
1$
0&
0?
b0 @
b100 A
1(
#2440
0(
#2460
b110 9
b10 :
b110 4
b10 3
bz0110 6
bz010 7
0;
0=
02
0/
bz0 8
b101 A
b1 @
1?
b101 +
b1 *
1)
1(
#2480
0(
#2500
b11 :
b111 9
1;
b11 3
b111 4
12
bz011 7
bz0111 6
1,
bz1 8
b110 +
b10 *
0)
0%
0$
0?
b10 @
b110 A
1(
#2520
0(
#2540
1<
11
b0 9
b0 :
1>
b0 4
10
b0 3
bz1 5
bz1000 6
bz100 7
0;
1=
02
1/
bz0 8
b111 A
b11 @
1?
b111 +
b11 *
1)
1(
#2560
0(
#2580
b1 :
b1 9
1;
b1 3
b1 4
1>
1<
12
10
11
bz001 7
bz0 5
bz0001 6
0,
0-
0.
bz1 8
b0 +
1#
b0 *
1'
0)
1%
1$
1&
1"
0?
b0 @
b0 A
1(
#2600
0(
#2620
b10 9
b10 :
b10 4
b10 3
bz0010 6
bz010 7
0;
0=
02
0/
bz0 8
b1 A
b1 @
1?
b1 +
b1 *
1)
1(
#2640
0(
#2660
b11 :
b11 9
1;
b11 3
b11 4
12
bz011 7
bz0011 6
1,
bz1 8
b10 +
b10 *
0)
0%
0$
0?
b10 @
b10 A
1(
#2680
0(
#2700
b100 9
b0 :
0>
b100 4
00
b0 3
bz1 5
bz0100 6
bz100 7
0;
1=
02
1/
bz0 8
b11 A
b11 @
1?
b11 +
b11 *
1)
1(
#2720
0(
#2740
b1 :
b101 9
1<
1;
b1 3
11
b101 4
0>
12
00
bz001 7
bz0 5
bz0101 6
0,
1-
bz1 8
b100 +
b0 *
0'
0)
1%
1$
0&
0?
b0 @
b100 A
1(
#2760
0(
#2780
b110 9
b10 :
b110 4
b10 3
bz0110 6
bz010 7
0;
0=
02
0/
bz0 8
b101 A
b1 @
1?
b101 +
b1 *
1)
1(
#2800
0(
#2820
b11 :
b111 9
1;
b11 3
b111 4
12
bz011 7
bz0111 6
1,
bz1 8
b110 +
b10 *
0)
0%
0$
0?
b10 @
b110 A
1(
#2840
0(
#2860
0<
01
b0 9
b0 :
1>
b0 4
10
b0 3
bz1 5
bz1000 6
bz100 7
0;
1=
02
1/
bz0 8
b111 A
b11 @
1?
b111 +
b11 *
1)
1(
#2880
0(
#2900
b1 :
b1 9
1;
b1 3
b1 4
1>
0<
12
10
01
bz001 7
bz0 5
bz0001 6
0,
0-
1.
bz1 8
b0 +
0#
b0 *
1'
0)
1%
1$
1&
0"
0?
b0 @
b0 A
1(
#2920
0(
#2940
b10 9
b10 :
b10 4
b10 3
bz0010 6
bz010 7
0;
0=
02
0/
bz0 8
b1 A
b1 @
1?
b1 +
b1 *
1)
1(
#2960
0(
#2980
b11 :
b11 9
1;
b11 3
b11 4
12
bz011 7
bz0011 6
1,
bz1 8
b10 +
b10 *
0)
0%
0$
0?
b10 @
b10 A
1(
#3000
0(
#3020
b100 9
b0 :
0>
b100 4
00
b0 3
bz1 5
bz0100 6
bz100 7
0;
1=
02
1/
bz0 8
b11 A
b11 @
1?
b11 +
b11 *
1)
1(
